mygo/__init__.py
mygo_goto-0.1.0.dist-info/METADATA
mygo_goto-0.1.0.dist-info/WHEEL
mygo_goto-0.1.0.dist-info/licenses/LICENSE
mygo_goto-0.1.0.dist-info/RECORD
