Metadata-Version: 2.4
Name: mygo-goto
Version: 0.1.0
Summary: A Python package for MyGO(Simple Goto)
Project-URL: Homepage, https://github.com/AndreaFrederica/Python-Dream-It-s-MyGO
Project-URL: Repository, https://github.com/AndreaFrederica/Python-Dream-It-s-MyGO.git
Project-URL: Issues, https://github.com/AndreaFrederica/Python-Dream-It-s-MyGO/issues
Author-email: AndreaFrederica <andreafrederica@outlook.com>
License: MPL-2.0
License-File: LICENSE
Classifier: License :: OSI Approved :: Mozilla Public License 2.0 (MPL 2.0)
Classifier: Operating System :: OS Independent
Classifier: Programming Language :: Python :: 3
Requires-Python: >=3.12
Provides-Extra: dev
Requires-Dist: build>=1.2.0; extra == 'dev'
Requires-Dist: pip>=25.2; extra == 'dev'
Requires-Dist: setuptools>=80.9.0; extra == 'dev'
Requires-Dist: twine>=6.2.0; extra == 'dev'
Requires-Dist: wheel>=0.45.1; extra == 'dev'
